common/__init__.py
common/browser.py
common/my_sql.py
common/utils.py
rankset/__init__.py
rankset/common/__init__.py
rankset/common/api.py
rankset/common/browser.py
rankset/common/my_sql.py
rankset/common/utils.py
rr/__init__.py
rr/api.py
rr/browser.py
rr/my_sql.py
rr/shared_utils.py
rr/utils.py
rr_common_base-1.0.dist-info/LICENSE
rr_common_base-1.0.dist-info/METADATA
rr_common_base-1.0.dist-info/WHEEL
rr_common_base-1.0.dist-info/top_level.txt
rr_common_base-1.0.dist-info/RECORD
