Metadata-Version: 2.1
Name: rr-common-base
Version: 1.0
Summary: rr-base-package
Home-page: https://upload.pypi.org/legacy/
Author: RR Team
Author-email: rr@rr.co.il
License: MIT
Platform: UNKNOWN
Classifier: Programming Language :: Python :: 3
Classifier: License :: OSI Approved :: MIT License
Classifier: Operating System :: OS Independent
Requires-Python: >=3.8
License-File: LICENSE
Requires-Dist: mysql-connector-python (~=8.0.26)
Requires-Dist: selenium (==3.141.0)
Requires-Dist: selenium-wire
Requires-Dist: webdriver-manager (~=3.5.2)
Requires-Dist: twine (~=3.4.2)
Requires-Dist: wheel (~=0.37.0)
Requires-Dist: browsermob-proxy (==0.8.0)
Requires-Dist: pandas (~=1.4.1)
Requires-Dist: lxml
Requires-Dist: html5lib
Requires-Dist: streamlit
Requires-Dist: requests
Requires-Dist: alphabet-detector
Requires-Dist: googletrans (==3.1.0a0)
Requires-Dist: python-dateutil (~=2.8.2)
Requires-Dist: setuptools (~=57.0.0)
